{"ovwcj2ltSgNaSoM7MddTpQ==":"header-1200x461.jpg","GP8OYmse6PJKVOdODsxD3g==":"0-cover-jeep-lineup1605545178373-1440x637.jpg","M8PSB9iHzziVgKR5XxhrcQ==":"2023-jeep-compass-101-1669747450-640x480.jpg","T/4aWkwqv6tIvogMYIVYpw==":"download-298x169.jpg","e/WUn/CrXNN4XwLaDbNFEw==":"images%20(1)-275x183.jpg","f3mkDn+caQ1gfyoX/JUZ3A==":"jeep-renegade-trailhawk-2022-4.jpg.webp","grSOIII7VH1As71FIeLBug==":"jeep-wrangler-2024-696x396.jpg","wA6KYVQ2UKdchMy8GBG7mQ==":"foto730-34728-696x421.jpg","h4P/8MAy1ZXZLriitaz36g==":"jeep-compass-6177d4e20f514-650x430.jpg","Ob+B/4FoE3zt8yFBtf9w2Q==":"jeep-gladiator-rubicon-1280x720.jpg","Qc+gJHs0lhF54FO6vRwTTw==":"jeep-wrangler-6177d4f2124da-650x430.jpg","29xvb6JMr5M+0bjleAv8VQ==":"jeep_grand-cherokee-l_2021_1_27072021_49775_1280-960-696x522.jpg","rMU+K0FSJqw8glvkqSPYNg==":"bq1jizxmomk5fj9e1f8jpx3xp-906x509.jpg","2BJhRUxpmW0cQN7PVFSrUg==":"compass-1024x576.jpg","DngwheYLcGmr6VHDjiClQQ==":"jeep-compass-serie-s-2022-14-1280x768.jpg","ZI2A7xs6OVM5ZAOqB8vfhw==":"images%20(5)-275x183.jpg","Vzidp1wQCV05HPBpLPfAZg==":"foto730-34721-558x338.jpg","0eVd/WxrOOfpoO4hz+Y68A==":"foto730-34710-558x338.jpg","f2d+GN8EAsEEnOtYuZokkg==":"images%20(14)-275x183.jpg","heFV4wMG2vLzBQSM5HVlkg==":"images%20(2)-275x183.jpg","bmLzqzoLNdxg13PnfboBeA==":"foto+19+-+jeep+renegade+acabamento+dos+bancos-561x374.jpg","Qj2U6BKeaWvZ3R2rS6k3qA==":"427331184073502-561x421.jpg","BYewqRjJiGGGmpM1tZKTkA==":"renegade-interior-seating-modelizer-limited-mckinsley-black-ski-grey-desktop.jpg.img.1440-561x316.jpg","KSS+lMiAdYXmMnKZ2nmt3g==":"jeep_grand_commander_summit_65_edited-1280x767.jpg","RLXfV5TZwFgFYN1HDex01Q==":"jp024-020wr-scaled-e1680802590263-1200x800.jpg"}